steindamm/__init__.py
steindamm/base.py
steindamm/exceptions.py
steindamm/py.typed
steindamm/semaphore.lua
steindamm/semaphore.py
steindamm/token_bucket/local_token_bucket.py
steindamm/token_bucket/redis_token_bucket.py
steindamm/token_bucket/token_bucket.lua
steindamm/token_bucket/token_bucket.py
steindamm/token_bucket/token_bucket_base.py
steindamm-0.9.0.dist-info/WHEEL
steindamm-0.9.0.dist-info/METADATA
steindamm-0.9.0.dist-info/RECORD
